README
setup.cfg
setup.py
formprocess/__init__.py
formprocess/handler.py
formprocess/pylonshandler.py
formprocess/pyramidhandler.py
formprocess/utils.py
formprocess.egg-info/PKG-INFO
formprocess.egg-info/SOURCES.txt
formprocess.egg-info/dependency_links.txt
formprocess.egg-info/not-zip-safe
formprocess.egg-info/requires.txt
formprocess.egg-info/top_level.txt