Metadata-Version: 1.0
Name: formprocess
Version: 0.4.3
Summary: Form Process is a simple library for processing html forms.
Home-page: UNKNOWN
Author: Ian Wilson
Author-email: ian@laspilitas.com
License: BSD
Platform: UNKNOWN
Classifier: Development Status :: 3 - Alpha
Classifier: Topic :: Utilities
Classifier: License :: OSI Approved :: BSD License
